RobotKafkaLibrary/Consumer.py
RobotKafkaLibrary/Producer.py
RobotKafkaLibrary/__init__.py
robot_kafka_library-0.0.4.dist-info/METADATA
robot_kafka_library-0.0.4.dist-info/WHEEL
robot_kafka_library-0.0.4.dist-info/top_level.txt
robot_kafka_library-0.0.4.dist-info/RECORD
