Metadata-Version: 2.1
Name: robot-kafka-library
Version: 0.0.4
Summary: robotframework exetension lib for test kafka
Home-page: https://github.com/tarathep/robot-kafka-library
Author: tarathep
Author-email: bokie.tarathep@gmail.com
License: MIT
Platform: UNKNOWN
Classifier: Programming Language :: Python :: 3
Classifier: License :: OSI Approved :: MIT License
Requires-Dist: kafka-python
